<?xml version="1.0" encoding="UTF-8"?>
<document version="3">
<meta>
<attr name="docdate" id="docdate" year="2022" month="01" date="17" sdate="2022-01-17" day-number="738171" day="Monday" wdaynum="1">20220117</attr>
<attr name="tokeniser_version" date="20151216"/></meta>
<text>
<p><s id="s2"><w common="true" l="sewer" pws="yes" id="w13" p="NNP" headn="yes" group="B-NP">Sewer</w> <w l="line" pws="yes" id="w19" p="NN" headn="yes" group="I-NP">line</w> <w l="repair" pws="yes" id="w24" p="VBN" headv="yes" group="B-VP">repaired</w> <w pws="yes" id="w33" p="IN" group="B-PP">after</w> <w l="spill" pws="yes" id="w39" p="NN" headn="yes" group="B-NP">spill</w> <w pws="yes" id="w45" p="IN" group="B-PP">into</w> <w common="true" l="flat" pws="yes" id="w50" p="NNP" group="B-NP">Flat</w> <w common="true" l="creek" pws="yes" id="w55" p="NNP" group="I-NP">Creek</w> <w l="tributary" pws="yes" id="w61" p="NN" headn="yes" group="I-NP">tributary</w><w sb="true" pws="no" id="w70" p="." group="O">.</w></s> <s id="s3"><w pws="yes" id="w72" p="DT" group="B-NP">A</w> <w l="wastewater" pws="yes" id="w74" p="NN" headn="yes" group="I-NP">wastewater</w> <w l="overflow" pws="yes" id="w85" p="NN" event="true" headn="yes" group="I-NP">overflow</w> <w pws="yes" id="w94" p="IN" group="B-PP">within</w> <w pws="yes" id="w101" p="DT" group="B-NP">the</w> <w locname="single" l="gainesville" pws="yes" id="w105" p="NNP" headn="yes" group="I-NP">Gainesville</w> <w l="sewer" pws="yes" id="w117" p="NN" headn="yes" group="I-NP">sewer</w> <w l="system" pws="yes" id="w123" p="NN" headn="yes" group="I-NP">system</w> <w l="cause" pws="yes" id="w130" p="VBD" headv="yes" group="B-VP">caused</w> <w pws="yes" id="w137" p="IN" group="B-NP">about</w> <w pws="yes" id="w143" p="CD" group="I-NP">5,400</w> <w l="gallon" pws="yes" id="w149" p="NNS" headn="yes" group="I-NP">gallons</w> <w pws="yes" id="w157" p="TO" group="B-VP">to</w> <w l="flow" pws="yes" id="w160" p="VB" headv="yes" group="I-VP">flow</w> <w pws="yes" id="w165" p="IN" group="B-PP">into</w> <w pws="yes" id="w170" p="DT" group="B-NP">a</w> <w l="tributary" pws="yes" id="w172" p="NN" headn="yes" group="I-NP">tributary</w> <w pws="yes" id="w182" p="IN" group="B-PP">of</w> <w common="true" l="flat" pws="yes" id="w185" p="NNP" group="B-NP">Flat</w> <w common="true" l="creek" pws="yes" id="w190" p="NNP" group="I-NP">Creek</w> <w pws="yes" id="w196" p="DT" trel="same" quty="1" group="B-NP">this</w> <w l="afternoon" pws="yes" id="w201" p="NN" group="I-NP">afternoon</w><w sb="true" pws="no" id="w210" p="." group="O">.</w></s> <s id="s4"><w l="accord" pws="yes" id="w212" p="VBG" headv="yes" group="B-PP">According</w> <w pws="yes" id="w222" p="TO" group="I-PP">to</w> <w pws="yes" id="w225" p="DT" group="B-NP">the</w> <w locname="single" l="gainesville" pws="yes" id="w229" p="NNP" group="I-NP">Gainesville</w> <w common="true" l="public" pws="yes" id="w241" p="NNP" group="I-NP">Public</w> <w common="true" l="utility" pws="yes" id="w248" p="NNP" group="I-NP">Utilities</w> <w l="department" pws="yes" id="w258" p="NN" headn="yes" group="I-NP">department</w><w pws="no" id="w268" p="," group="O">,</w> <w pws="yes" id="w270" p="DT" group="B-NP">the</w> <w l="spill" pws="yes" id="w274" p="NN" headn="yes" group="I-NP">spill</w> <w l="be" pws="yes" id="w280" p="VBD" group="B-VP">was</w> <w l="notice" pws="yes" id="w284" p="VBN" headv="yes" group="I-VP">noticed</w> <w pws="yes" id="w292" p="IN" group="B-PP">at</w> <w pws="yes" id="w295" p="RB" group="B-ADVP">about</w> <w pws="yes" id="w301" p="CD" group="B-NP">1:45</w> <w l="p.m." pws="yes" id="w306" p="NN" group="I-NP">p.m.</w> <w pws="yes" id="w311" p="IN" group="B-PP">by</w> <w pws="yes" id="w314" p="DT" group="B-NP">an</w> <w l="attendant" pws="yes" id="w317" p="NN" headn="yes" group="I-NP">attendant</w> <w pws="yes" id="w327" p="IN" group="B-PP">at</w> <w pws="yes" id="w330" p="DT" group="B-NP">the</w> <w common="true" l="orchard" pws="yes" id="w334" p="NNP" headn="yes" group="I-NP">Orchard</w> <w common="true" l="brook" pws="yes" id="w342" p="NNP" wfirstn="true" headn="yes" group="I-NP">Brook</w> <w l="apartment" pws="yes" id="w348" p="NNS" headn="yes" group="I-NP">apartments</w> <w pws="yes" id="w359" p="IN" group="B-PP">in</w> <w pws="yes" id="w362" p="DT" group="B-NP">the</w> <w pws="yes" id="w366" p="CD" quty="2900" group="B-NP">2900</w> <w l="block" pws="yes" id="w371" p="NN" headn="yes" group="I-NP">block</w> <w pws="yes" id="w377" p="IN" group="B-PP">of</w> <w locname="single" l="mcever" pws="yes" id="w380" p="NNP" headn="yes" group="B-NP">McEver</w> <w common="true" l="road" pws="yes" id="w387" p="NNP" headn="yes" group="I-NP">Road</w><w sb="true" pws="no" id="w391" p="." group="O">.</w></s> <s id="s5"><w common="true" l="utility" pws="yes" id="w393" p="NN" headn="yes" group="B-NP">Utility</w> <w prof="true" l="worker" pws="yes" id="w401" p="NNS" headn="yes" group="I-NP">workers</w> <w l="find" pws="yes" id="w409" p="VBD" headv="yes" group="B-VP">found</w> <w l="debris" pws="yes" id="w415" p="NN" headn="yes" group="B-NP">debris</w> <w l="block" pws="yes" id="w422" p="VBG" headv="yes" group="B-VP">blocking</w> <w pws="yes" id="w431" p="DT" group="B-NP">a</w> <w l="sewer" pws="yes" id="w433" p="NN" headn="yes" group="I-NP">sewer</w> <w l="line" pws="yes" id="w439" p="NN" headn="yes" group="I-NP">line</w> <w pws="yes" id="w444" p="CC" group="O">and</w> <w l="repair" pws="yes" id="w448" p="VBD" headv="yes" group="B-VP">repaired</w> <w pws="yes" id="w457" p="DT" group="B-NP">the</w> <w state="true" l="problem" pws="yes" id="w461" p="NN" tmln="true" headn="yes" group="I-NP">problem</w> <w pws="yes" id="w469" p="IN" group="B-PP">in</w> <w pws="yes" id="w472" p="IN" group="B-PP">about</w> <w pws="yes" id="w478" p="DT" group="B-NP">an</w> <w l="hour" pws="yes" id="w481" p="NN" headn="yes" group="I-NP">hour</w><w sb="true" pws="no" id="w485" p="." group="O">.</w></s> <s id="s6"><w pws="yes" id="w487" p="IN" group="B-PP">After</w> <w l="clean" pws="yes" id="w493" p="VBG" headv="yes" group="B-VP">cleaning</w> <w pws="yes" id="w502" p="RP" group="O">up</w> <w pws="yes" id="w505" p="DT" group="B-NP">the</w> <w l="area" pws="yes" id="w509" p="NN" headn="yes" group="I-NP">area</w><w pws="no" id="w513" p="," group="O">,</w> <w pws="yes" id="w515" p="PRP" group="B-NP">they</w> <w l="post" pws="yes" id="w520" p="VBD" class="reporting" headv="yes" group="B-VP">posted</w> <w l="warn" pws="yes" id="w527" p="VBG" headv="yes" group="B-VP">warning</w> <w l="sign" pws="yes" id="w535" p="NNS" tmln="true" headn="yes" group="B-NP">signs</w> <w pws="yes" id="w541" p="CC" group="O">and</w> <w l="contact" pws="yes" id="w545" p="VBN" headv="yes" group="B-NP">contacted</w> <w common="true" l="hall" pws="yes" id="w555" p="NNP" group="I-NP">Hall</w> <w l="county" pws="yes" id="w560" p="NNP" group="I-NP">County</w> <w common="true" l="environmental" pws="yes" id="w567" p="NNP" group="I-NP">Environmental</w> <w state="true" common="true" l="health" pws="yes" id="w581" p="NNP" group="I-NP">Health</w> <w pws="yes" id="w588" p="CC" group="O">and</w> <w pws="yes" id="w592" p="DT" group="B-NP">the</w> <w l="georgium" pws="yes" id="w596" p="NNP" pername="true" country="true" wfirstn="true" group="I-NP">Georgia</w> <w common="true" l="environmental" pws="yes" id="w604" p="NNP" group="I-NP">Environmental</w> <w common="true" vstem="protect" l="protection" pws="yes" id="w618" p="NNP" event="true" tmln="true" group="I-NP">Protection</w> <w common="true" vstem="divide" l="division" pws="yes" id="w629" p="NNP" group="I-NP">Division</w><w sb="true" pws="no" id="w637" p="." group="O">.</w></s> <s id="s7"><w pws="yes" id="w639" p="DT" group="B-NP">The</w> <w l="spill" pws="yes" id="w643" p="NN" headn="yes" group="I-NP">spill</w> <w l="be" pws="yes" id="w649" p="VBZ" group="B-VP">is</w> <w pws="yes" id="w652" p="RB" neg="yes" group="I-VP">not</w> <w l="consider" pws="yes" id="w656" p="VBN" class="istate" headv="yes" group="I-VP">considered</w> <w pws="yes" id="w667" p="JJ" group="B-ADJP">major</w><w pws="no" id="w672" p="," group="O">,</w> <w pws="yes" id="w674" p="CC" group="O">but</w> <w pws="yes" id="w678" p="DT" group="B-NP">the</w> <w l="epd" pws="yes" id="w682" p="NNP" headn="yes" group="I-NP">EPD</w> <w l="have" pws="yes" id="w686" p="VBZ" headv="yes" group="B-VP">has</w> <w pws="yes" id="w690" p="DT" group="B-NP">a</w> <w pws="yes" id="w692" p="JJ" group="I-NP">zero-tolerance</w> <w l="policy" pws="yes" id="w707" p="NN" tmln="true" headn="yes" group="I-NP">policy</w> <w pws="yes" id="w714" p="IN" group="B-PP">for</w> <w l="wastewater" pws="yes" id="w718" p="NN" headn="yes" group="B-NP">wastewater</w> <w l="overflow" pws="yes" id="w729" p="NNS" event="true" headn="yes" group="I-NP">overflows</w> <w pws="yes" id="w739" p="WDT" group="B-NP">that</w> <w l="affect" pws="yes" id="w744" p="VBP" headv="yes" group="B-VP">affect</w> <w common="true" l="lake" pws="yes" id="w751" p="NNP" group="B-NP">Lake</w> <w l="lanier" pws="yes" id="w756" p="NNP" group="I-NP">Lanier</w><w pws="no" id="w762" p="POS" group="I-NP">'s</w> <w l="watershed" pws="yes" id="w765" p="NN" headn="yes" group="I-NP">watershed</w><w sb="true" pws="no" id="w774" p="." group="O">.</w></s> <s id="s8"><w pws="yes" id="w776" p="IN" group="B-PP">For</w> <w pws="yes" id="w780" p="JJR" group="B-NP">more</w> <w l="information" pws="yes" id="w785" p="NN" headn="yes" group="I-NP">information</w><w pws="no" id="w796" p="," group="O">,</w> <w vstem="contact" l="contact" pws="yes" id="w798" p="NN" headn="yes" group="B-NP">contact</w> <w locname="single" l="horace" pws="yes" id="w806" p="NNP" wfirstn="true" group="B-NP">Horace</w> <w l="gee" pws="yes" id="w813" p="NNP" wfirstn="true" group="I-NP">Gee</w><w pws="no" id="w816" p="," group="O">,</w> <w locname="single" l="gainesville" pws="yes" id="w818" p="NNP" group="B-NP">Gainesville</w> <w common="true" l="environmental" pws="yes" id="w830" p="NNP" group="I-NP">Environmental</w> <w common="true" vstem="serve" l="service" pws="yes" id="w844" p="NNP" event="true" tmln="true" group="I-NP">Services</w> <w prof="true" l="administrator" pws="yes" id="w853" p="NN" headn="yes" group="I-NP">administrator</w><w pws="no" id="w866" p="," group="O">,</w> <w pws="yes" id="w868" p="IN" group="B-PP">at</w> <w pws="yes" id="w871" p="CD" headn="yes" group="B-NP">770-532-7462</w><w sb="true" pws="no" id="w883" p="." group="O">.</w></s></p>
</text>
<standoff>
<ents source="ner-rb">
  <ent id="rb1" type="location" lat="34.24593" long="-83.9299" gazref="geonames:4195280" in-country="US" feat-type="ppl">
    <parts>
      <part ew="w55" sw="w50">Flat Creek</part>
    </parts>
  </ent>
  <ent id="rb2" type="location" lat="34.24593" long="-83.9299" gazref="geonames:4195280" in-country="US" feat-type="ppl">
    <parts>
      <part ew="w190" sw="w185">Flat Creek</part>
    </parts>
  </ent>
  <ent id="rb3" tval="1" trel="same" type="time">
    <parts>
      <part ew="w201" sw="w196">this afternoon</part>
    </parts>
  </ent>
  <ent id="rb5" tval="1:45" type="time">
    <parts>
      <part ew="w306" sw="w301">1:45 p.m.</part>
    </parts>
  </ent>
  <ent id="rb6" type="date" year="2900">
    <parts>
      <part ew="w366" sw="w366">2900</part>
    </parts>
  </ent>
  <ent id="rb9" type="location" lat="34.16038" long="-84.07352" gazref="geonames:4204680" in-country="US" feat-type="water">
    <parts>
      <part ew="w756" sw="w751">Lake Lanier</part>
    </parts>
  </ent>
  <ent id="rb10" type="person">
    <parts>
      <part ew="w813" sw="w806">Horace Gee</part>
    </parts>
  </ent>
</ents>
<ents source="events">
  <ent tense="nonfin" voice="pass" asp="simple" modal="no" id="ev1" subtype="repair" type="event"><parts><part ew="w24" sw="w24">repaired</part></parts></ent>
  <ent tense="past" voice="act" asp="simple" modal="no" id="ev2" subtype="cause" type="event"><parts><part ew="w130" sw="w130">caused</part></parts></ent>
  <ent tense="inf" voice="act" asp="simple" modal="no" id="ev3" subtype="flow" type="event"><parts><part ew="w160" sw="w160">flow</part></parts></ent>
  <ent tense="past" voice="pass" asp="simple" modal="no" id="ev4" subtype="notice" type="event"><parts><part ew="w284" sw="w284">noticed</part></parts></ent>
  <ent tense="past" voice="act" asp="simple" modal="no" id="ev5" subtype="find" type="event"><parts><part ew="w409" sw="w409">found</part></parts></ent>
  <ent tense="nonfin" voice="act" asp="prog" modal="no" id="ev6" subtype="block" type="event"><parts><part ew="w422" sw="w422">blocking</part></parts></ent>
  <ent tense="past" voice="act" asp="simple" modal="no" id="ev7" subtype="repair" type="event"><parts><part ew="w448" sw="w448">repaired</part></parts></ent>
  <ent tense="nonfin" voice="act" asp="prog" modal="no" id="ev8" subtype="clean" type="event"><parts><part ew="w493" sw="w493">cleaning</part></parts></ent>
  <ent tense="past" voice="act" asp="simple" modal="no" id="ev9" subtype="post" type="event"><parts><part ew="w520" sw="w520">posted</part></parts></ent>
  <ent tense="nonfin" voice="act" asp="prog" modal="no" id="ev10" subtype="warn" type="event"><parts><part ew="w527" sw="w527">warning</part></parts></ent>
  <ent tense="pres" voice="pass" asp="simple" modal="no" neg="yes" id="ev11" subtype="consider" type="event"><parts><part ew="w656" sw="w656">considered</part></parts></ent>
  <ent tense="presorbase" voice="act" asp="simple" modal="no" id="ev12" subtype="affect" type="event"><parts><part ew="w744" sw="w744">affect</part></parts></ent>
</ents>
<relations source="temprel">
  <relation id="rbr1" type="beforeorincl" text="caused">
    <argument arg1="true" ref="ev2"/>
    <argument arg2="true" ref="docdate"/>
  </relation>
  <relation id="rbr2" type="beforeorincl" text="was noticed">
    <argument arg1="true" ref="ev4"/>
    <argument arg2="true" ref="docdate"/>
  </relation>
  <relation id="rbr3" type="beforeorincl" text="found">
    <argument arg1="true" ref="ev5"/>
    <argument arg2="true" ref="docdate"/>
  </relation>
  <relation id="rbr4" type="beforeorincl" text="repaired">
    <argument arg1="true" ref="ev7"/>
    <argument arg2="true" ref="docdate"/>
  </relation>
  <relation id="rbr5" type="beforeorincl" text="posted">
    <argument arg1="true" ref="ev9"/>
    <argument arg2="true" ref="docdate"/>
  </relation>
</relations></standoff></document>
