<?xml version="1.0" encoding="UTF-8"?>
<data date-time-format="iso8601">
  <event start="0000-00-00T00:00:00Z" title="stood for the initials for Charles Oliver Wellington (C.O.W.) In the 1950s">
    Wellington was originally the world's largest strawberry patch on land called the Flying Cow Ranch; "Flying" because the founder was an aviator, and "Cow" stood for the initials for Charles Oliver Wellington (C.O.W.) In the 1950s, Mr. Wellington bought 18,000 acres (73 km2) of central Palm Beach County swampland, which would eventually become the Village of Wellington.
  </event>
  <event start="0000-00-00T00:00:00Z" title="approved by Palm Beach County in 1972">
    Wellington began as a planned unit development approved by Palm Beach County in 1972, and up until 1990, it functioned as a sprawling bedroom community with few shopping centers or restaurants until it was incorporated in December 1995.
  </event>
  <event start="0000-00-00T00:00:00Z" title="1990, it functioned">
    Wellington began as a planned unit development approved by Palm Beach County in 1972, and up until 1990, it functioned as a sprawling bedroom community with few shopping centers or restaurants until it was incorporated in December 1995.
  </event>
  <event start="1995-12-01T00:00:00Z" end="1995-12-31T00:00:00Z" isDuration="true" title="was incorporated in December 1995">
    Wellington began as a planned unit development approved by Palm Beach County in 1972, and up until 1990, it functioned as a sprawling bedroom community with few shopping centers or restaurants until it was incorporated in December 1995.
  </event>
  <event start="0000-00-00T00:00:00Z" title="now become">
    It has now become known as an international center for equestrian sports.
  </event>
</data>
