<?xml version="1.0" encoding="UTF-8"?>
<document version="3">
<meta>
<attr name="docdate" id="docdate" year="2022" month="01" date="18" sdate="2022-01-18" day-number="738172" day="Tuesday" wdaynum="2">20220118</attr>
<attr name="tokeniser_version" date="20151216"/></meta>
<text>
<p><s id="s2"><w l="wellington" pws="yes" id="w13" p="NNP" wfirstn="true" headn="yes" group="B-NP">Wellington</w> <w l="be" pws="yes" id="w24" p="VBZ" headv="yes" group="B-VP">is</w> <w pws="yes" id="w27" p="DT" group="B-NP">a</w> <w l="town" pws="yes" id="w29" p="NN" headn="yes" group="I-NP">town</w> <w pws="yes" id="w34" p="IN" group="B-PP">in</w> <w pws="yes" id="w37" p="DT" group="B-NP">the</w> <w common="true" pws="yes" id="w41" p="JJ" group="I-NP">Western</w> <w common="true" l="cape" pws="yes" id="w49" p="NNP" headn="yes" group="I-NP">Cape</w> <w l="wineland" pws="yes" id="w54" p="NNS" headn="yes" group="I-NP">Winelands</w><w pws="no" id="w63" p="," group="O">,</w> <w pws="yes" id="w65" p="DT" group="B-NP">a</w> <w pws="yes" id="w67" p="CD" quty="45" headn="yes" group="I-NP">45</w><w pws="no" id="w69" p=":" headn="yes" group="I-NP">-</w><w l="minute" pws="no" id="w70" p="NN" headn="yes" group="I-NP">minute</w> <w l="drive" pws="yes" id="w77" p="NN" event="true" tmln="true" headn="yes" group="I-NP">drive</w> <w pws="yes" id="w83" p="IN" group="B-PP">from</w> <w common="true" l="cape" pws="yes" id="w88" p="NNP" headn="yes" group="B-NP">Cape</w> <w common="true" l="town" pws="yes" id="w93" p="NNP" headn="yes" group="I-NP">Town</w><w pws="no" id="w97" p="," group="O">,</w> <w pws="yes" id="w99" p="IN" group="B-PP">in</w> <w common="true" l="south" pws="yes" id="w102" p="NNP" country="true" group="B-NP">South</w> <w l="africa" pws="yes" id="w108" p="NNP" country="true" group="I-NP">Africa</w> <w pws="yes" id="w115" p="IN" group="B-PP">with</w> <w pws="yes" id="w120" p="DT" group="B-NP">a</w> <w vstem="populate" l="population" pws="yes" id="w122" p="NN" headn="yes" group="I-NP">population</w> <w pws="yes" id="w133" p="IN" group="B-PP">of</w> <w pws="yes" id="w136" p="RB" headn="yes" group="B-NP">approximately</w> <w pws="yes" id="w150" p="CD" headn="yes" group="I-NP">62,000</w><w sb="true" pws="no" id="w156" p="." group="O">.</w></s> <s id="s3"><w l="wellington" pws="yes" id="w158" p="NNP" wfirstn="true" headn="yes" group="B-NP">Wellington</w><w pws="no" id="w168" p="POS" group="I-NP">'s</w> <w l="economy" pws="yes" id="w171" p="NN" headn="yes" group="I-NP">economy</w> <w l="be" pws="yes" id="w179" p="VBZ" group="B-VP">is</w> <w l="center" pws="yes" id="w182" p="VBN" headv="yes" group="I-VP">centered</w> <w pws="yes" id="w191" p="IN" group="B-PP">on</w> <w l="agriculture" pws="yes" id="w194" p="NN" event="true" headn="yes" group="B-NP">agriculture</w> <w pws="yes" id="w206" p="JJ" group="B-ADJP">such</w> <w pws="yes" id="w211" p="IN" group="B-PP">as</w> <w l="wine" pws="yes" id="w214" p="NN" headn="yes" group="B-NP">wine</w><w pws="no" id="w218" p="," group="O">,</w> <w l="table" pws="yes" id="w220" p="NN" headn="yes" group="B-NP">table</w> <w l="grape" pws="yes" id="w226" p="NNS" headn="yes" group="I-NP">grapes</w><w pws="no" id="w232" p="," group="O">,</w> <w pws="yes" id="w234" p="JJ" group="B-NP">deciduous</w> <w l="fruit" pws="yes" id="w244" p="NN" headn="yes" group="I-NP">fruit</w> <w pws="yes" id="w250" p="CC" group="O">and</w> <w pws="yes" id="w254" p="DT" group="B-NP">a</w> <w l="brandy" pws="yes" id="w256" p="NN" headn="yes" group="I-NP">brandy</w> <w l="industry" pws="yes" id="w263" p="NN" headn="yes" group="I-NP">industry</w><w sb="true" pws="no" id="w271" p="." group="O">.</w></s> <s id="s4"><w pws="yes" id="w273" p="DT" group="B-NP">The</w> <w l="town" pws="yes" id="w277" p="NN" headn="yes" group="I-NP">town</w> <w l="be" pws="yes" id="w282" p="VBZ" group="B-VP">is</w> <w l="locate" pws="yes" id="w285" p="VBN" headv="yes" group="I-VP">located</w> <w pws="yes" id="w293" p="CD" quty="75" group="B-NP">75</w> <w l="km" pws="yes" id="w296" p="NN" headn="yes" group="I-NP">km</w> <w l="north-east" pws="yes" id="w299" p="NN" headn="yes" group="I-NP">north-east</w> <w pws="yes" id="w310" p="IN" group="B-PP">of</w> <w common="true" l="cape" pws="yes" id="w313" p="NNP" headn="yes" group="B-NP">Cape</w> <w common="true" l="town" pws="yes" id="w318" p="NNP" headn="yes" group="I-NP">Town</w><w pws="no" id="w322" p="," group="O">,</w> <w l="reach" pws="yes" id="w324" p="VBN" headv="yes" group="B-VP">reached</w> <w pws="yes" id="w332" p="IN" group="B-PP">by</w> <w pws="yes" id="w335" p="DT" group="B-NP">the</w> <w l="n1" pws="yes" id="w339" p="NNP" headn="yes" group="I-NP">N1</w> <w l="motorway" pws="yes" id="w342" p="NN" headn="yes" group="I-NP">motorway</w> <w pws="yes" id="w351" p="CC" headn="yes" group="I-NP">and</w> <w l="r44" pws="yes" id="w355" p="NN" headn="yes" group="I-NP">R44</w><w sb="true" pws="no" id="w358" p="." group="O">.</w></s> <s id="s5"><w tmla="true" common="true" pws="yes" id="w360" p="JJ" group="B-ADJP">Due</w> <w pws="yes" id="w364" p="TO" group="B-PP">to</w> <w pws="yes" id="w367" p="DT" group="B-NP">the</w> <w vstem="grow" l="growth" pws="yes" id="w371" p="NN" tmln="true" headn="yes" group="I-NP">growth</w> <w pws="yes" id="w378" p="IN" group="B-PP">of</w> <w pws="yes" id="w381" p="DT" group="B-NP">the</w> <w l="mbekwenus" pws="yes" id="w385" p="NNP" headn="yes" group="I-NP">Mbekweni</w> <w l="township" pws="yes" id="w394" p="NN" headn="yes" group="I-NP">township</w> <w l="south" pws="yes" id="w403" p="NN" headn="yes" group="I-NP">south</w> <w pws="yes" id="w409" p="IN" group="B-PP">of</w> <w l="town" pws="yes" id="w412" p="NN" headn="yes" group="B-NP">town</w><w pws="no" id="w416" p="," group="O">,</w> <w pws="yes" id="w418" p="PRP" group="B-NP">it</w> <w pws="yes" id="w421" p="RB" tref="present" group="B-NP">now</w> <w l="form" pws="yes" id="w425" p="VBZ" headv="yes" group="B-VP">forms</w> <w pws="yes" id="w431" p="DT" group="O">a</w> <w pws="yes" id="w433" p="FW" group="O">de</w> <w pws="yes" id="w436" p="FW" group="O">facto</w> <w pws="yes" id="w442" p="JJ" group="B-NP">urban</w> <w l="unit" pws="yes" id="w448" p="NN" headn="yes" group="I-NP">unit</w> <w pws="yes" id="w453" p="IN" group="B-PP">with</w> <w locname="single" l="paarl" pws="yes" id="w458" p="NNP" group="B-NP">Paarl</w><w pws="no" id="w463" p="," group="O">,</w> <w pws="yes" id="w465" p="RB" group="B-ADVP">just</w> <w pws="yes" id="w470" p="CD" quty="10" group="B-NP">10</w> <w l="km" pws="yes" id="w473" p="NN" headn="yes" group="I-NP">km</w> <w pws="yes" id="w476" p="TO" group="B-PP">to</w> <w pws="yes" id="w479" p="DT" group="B-NP">the</w> <w l="south" pws="yes" id="w483" p="NN" headn="yes" group="I-NP">south</w><w sb="true" pws="no" id="w488" p="." group="O">.</w></s> <s id="s6"><w l="wellington" pws="yes" id="w490" p="NNP" wfirstn="true" headn="yes" group="B-NP">Wellington</w> <w l="be" pws="yes" id="w501" p="VBZ" group="B-VP">is</w> <w l="situate" pws="yes" id="w504" p="VBN" headv="yes" group="I-VP">situated</w> <w pws="yes" id="w513" p="IN" group="B-PP">at</w> <w pws="yes" id="w516" p="DT" group="B-NP">the</w> <w l="foot" pws="yes" id="w520" p="NN" headn="yes" group="I-NP">foot</w> <w pws="yes" id="w525" p="IN" group="B-PP">of</w> <w pws="yes" id="w528" p="DT" group="B-NP">the</w> <w locname="single" l="groenberg" pws="yes" id="w532" p="NNP" group="I-NP">Groenberg</w> <w pws="yes" id="w542" p="IN" group="B-PP">on</w> <w pws="yes" id="w545" p="DT" group="B-NP">the</w> <w l="bank" pws="yes" id="w549" p="NNS" headn="yes" group="I-NP">banks</w> <w pws="yes" id="w555" p="IN" group="B-PP">of</w> <w pws="yes" id="w558" p="DT" group="B-NP">the</w> <w l="kromme" pws="yes" id="w562" p="NNP" group="I-NP">Kromme</w> <w l="rivier" pws="yes" id="w569" p="NNP" group="I-NP">Rivier</w> <w pws="yes" id="w576" p="(" group="O">(</w><w common="true" l="dutch" pws="no" id="w577" p="NNP" locadj="true" wfirstn="true" group="B-NP">Dutch</w> <w pws="yes" id="w583" p="IN" group="I-NP">for</w> <w common="true" l="bend" pws="yes" id="w587" p="NNP" group="I-NP">Bend</w> <w common="true" l="river" pws="yes" id="w592" p="NNP" group="I-NP">River</w><w pws="no" id="w597" p=")" group="O">)</w> <w pws="yes" id="w599" p="CC" group="O">and</w> <w l="form" pws="yes" id="w603" p="VBZ" headv="yes" group="B-VP">forms</w> <w pws="yes" id="w609" p="DT" group="B-NP">the</w> <w l="center" pws="yes" id="w613" p="NN" headn="yes" group="I-NP">center</w> <w pws="yes" id="w620" p="IN" group="B-PP">of</w> <w pws="yes" id="w623" p="DT" group="B-NP">the</w> <w common="true" l="cape" pws="yes" id="w627" p="NNP" headn="yes" group="I-NP">Cape</w> <w l="wineland" pws="yes" id="w632" p="NNS" headn="yes" group="I-NP">Winelands</w> <w pws="yes" id="w642" p="IN" group="B-PP">with</w> <w pws="yes" id="w647" p="PRP$" group="B-NP">its</w> <w l="picturesque" pws="yes" id="w651" p="NN" headn="yes" group="I-NP">picturesque</w> <w state="true" l="environment" pws="yes" id="w663" p="NN" headn="yes" group="I-NP">environment</w> <w pws="yes" id="w675" p="CC" group="O">and</w> <w pws="yes" id="w679" p="JJ" group="B-NP">numerous</w> <w l="winerie." pws="yes" id="w688" p="NNS" headn="yes" group="I-NP">wineries.</w><w pws="no" id="w697" p="DT" group="B-NP">The</w> <w l="town" pws="yes" id="w701" p="NN" headn="yes" group="I-NP">town</w> <w l="be" pws="yes" id="w706" p="VBZ" headv="yes" group="B-VP">is</w> <w pws="yes" id="w709" p="IN" group="B-PP">at</w> <w pws="yes" id="w712" p="DT" group="B-NP">the</w> <w l="base" pws="yes" id="w716" p="NN" headn="yes" group="I-NP">base</w> <w pws="yes" id="w721" p="IN" group="B-PP">of</w> <w pws="yes" id="w724" p="CD" quty="1" headn="yes" group="B-NP">one</w> <w pws="yes" id="w728" p="IN" group="I-NP">of</w> <w pws="yes" id="w731" p="DT" group="I-NP">the</w> <w pws="yes" id="w735" p="JJS" group="I-NP">oldest</w> <w l="mountain" pws="yes" id="w742" p="NN" headn="yes" group="I-NP">mountain</w> <w l="pass" pws="yes" id="w751" p="NNS" headn="yes" group="I-NP">passes</w> <w pws="yes" id="w758" p="IN" group="B-PP">in</w> <w pws="yes" id="w761" p="DT" group="B-NP">the</w> <w l="country" pws="yes" id="w765" p="NN" headn="yes" group="I-NP">country</w><w pws="no" id="w772" p="," group="O">,</w> <w l="bain" pws="yes" id="w774" p="NNP" group="B-NP">Bain</w><w pws="no" id="w778" p="POS" group="I-NP">'s</w> <w l="kloof" pws="yes" id="w781" p="NNP" group="I-NP">Kloof</w> <w l="pass" pws="yes" id="w787" p="NNP" group="I-NP">Pass</w><w pws="no" id="w791" p="," group="O">,</w> <w l="build" pws="yes" id="w793" p="VBN" headv="yes" group="B-VP">built</w> <w pws="yes" id="w799" p="IN" group="B-PP">by</w> <w prof="true" l="master" pws="yes" id="w802" p="NN" headn="yes" group="B-NP">master</w> <w l="road-builder" pws="yes" id="w809" p="NN" headn="yes" group="I-NP">road-builder</w> <w wiki="B-wper" l="andrew" pws="yes" id="w822" p="NNP" pername="true" wfirstn="true" group="B-NP">Andrew</w> <w wiki="I-wper" locname="single" l="gedde" pws="yes" id="w829" p="NNP" group="I-NP">Geddes</w> <w wiki="I-wper" locname="single" l="bain" pws="yes" id="w836" p="NNP" group="I-NP">Bain</w><w sb="true" pws="no" id="w840" p="." group="O">.</w></s> <s id="s7"><w pws="yes" id="w842" p="DT" group="B-NP">The</w> <w l="town" pws="yes" id="w846" p="NN" headn="yes" group="I-NP">town</w> <w l="be" pws="yes" id="w851" p="VBZ" headv="yes" group="B-VP">is</w> <w pws="yes" id="w854" p="DT" group="B-NP">the</w> <w l="home" pws="yes" id="w858" p="NN" headn="yes" group="I-NP">home</w> <w pws="yes" id="w863" p="IN" group="B-PP">of</w> <w pws="yes" id="w866" p="DT" group="B-NP">the</w> <w locname="single" l="boland" pws="yes" id="w870" p="NNP" group="I-NP">Boland</w> <w common="true" l="rugby" pws="yes" id="w877" p="NNP" event="true" group="I-NP">Rugby</w> <w common="true" l="union" pws="yes" id="w883" p="NNP" group="I-NP">Union</w> <w pws="yes" id="w889" p="CC" group="O">and</w> <w pws="yes" id="w893" p="DT" group="B-NP">the</w> <w pws="yes" id="w897" p="JJ" group="I-NP">professional</w> <w l="rugby" pws="yes" id="w910" p="NN" event="true" headn="yes" group="I-NP">rugby</w> <w l="team" pws="yes" id="w916" p="NN" headn="yes" group="I-NP">team</w> <w pws="yes" id="w921" p="DT" group="B-NP">the</w> <w locname="single" l="boland" pws="yes" id="w925" p="NNP" headn="yes" group="I-NP">Boland</w> <w l="kavalier" pws="yes" id="w932" p="NNP" headn="yes" group="I-NP">Kavaliers</w><w sb="true" pws="no" id="w941" p="." group="O">.</w></s> <s id="s8"><w pws="yes" id="w943" p="DT" group="B-NP">The</w> <w l="town" pws="yes" id="w947" p="NN" headn="yes" group="I-NP">town</w> <w l="be" pws="yes" id="w952" p="VBZ" headv="yes" group="B-VP">is</w> <w pws="yes" id="w955" p="RB" group="B-ADVP">also</w> <w pws="yes" id="w960" p="DT" group="B-NP">an</w> <w pws="yes" id="w963" p="JJ" group="I-NP">academic</w> <w l="centre" pws="yes" id="w972" p="NN" headn="yes" group="I-NP">centre</w><w pws="no" id="w978" p="," group="O">,</w> <w pws="yes" id="w980" p="IN" group="B-PP">with</w> <w common="true" l="cape" pws="yes" id="w985" p="NNP" headn="yes" group="B-NP">Cape</w> <w common="true" l="peninsula" pws="yes" id="w990" p="NNP" headn="yes" group="I-NP">Peninsula</w> <w common="true" l="university" pws="yes" id="w1000" p="NNP" headn="yes" group="I-NP">University</w> <w pws="yes" id="w1011" p="IN" group="B-PP">of</w> <w common="true" l="technology" pws="yes" id="w1014" p="NNP" event="true" tmln="true" headn="yes" group="B-NP">Technology</w><w pws="no" id="w1024" p="," group="O">,</w> <w pws="yes" id="w1026" p="DT" group="B-NP">the</w> <w l="timothy" pws="yes" id="w1030" p="NNP" pername="true" wfirstn="true" group="I-NP">Timothy</w> <w common="true" l="ministry" pws="yes" id="w1038" p="NNP" group="I-NP">Ministry</w> <w common="true" l="team" pws="yes" id="w1047" p="NNP" group="I-NP">Team</w><w pws="no" id="w1051" p="," group="I-NP">,</w> <w l="bible" pws="yes" id="w1053" p="NNP" group="I-NP">Bible</w> <w common="true" l="media" pws="yes" id="w1059" p="NNP" group="I-NP">Media</w><w pws="no" id="w1064" p="," group="I-NP">,</w> <w locname="single" l="huguenot" pws="yes" id="w1066" p="NNP" group="I-NP">Huguenot</w> <w common="true" l="high" pws="yes" id="w1075" p="NNP" tmln="true" group="I-NP">High</w> <w common="true" l="school" pws="yes" id="w1080" p="NNP" group="I-NP">School</w> <w pws="yes" id="w1087" p="CC" group="I-NP">and</w> <w locname="single" l="weltevrede" pws="yes" id="w1091" p="NNP" group="I-NP">Weltevrede</w> <w common="true" l="senior" pws="yes" id="w1102" p="NNP" group="I-NP">Senior</w> <w common="true" l="secondary" pws="yes" id="w1109" p="NNP" group="I-NP">Secondary</w> <w common="true" l="school" pws="yes" id="w1119" p="NNP" group="I-NP">School</w><w pws="no" id="w1125" p="," group="I-NP">,</w> <w l="bergriver" pws="yes" id="w1127" p="NNP" group="I-NP">Bergriver</w> <w common="true" l="senior" pws="yes" id="w1137" p="NNP" group="I-NP">Senior</w> <w common="true" l="secondary" pws="yes" id="w1144" p="NNP" group="I-NP">Secondary</w> <w common="true" l="school" pws="yes" id="w1154" p="NNP" group="I-NP">School</w> <w l="amongst" pws="yes" id="w1161" p="NN" headn="yes" group="I-NP">amongst</w> <w l="other" pws="yes" id="w1169" p="NNS" headn="yes" group="I-NP">others</w><w sb="true" pws="no" id="w1175" p="." group="O">.</w></s></p>
</text>
<standoff>
<ents source="ner-rb">
  <ent id="rb1" type="location" lat="" long="" gazref="">
    <parts>
      <part ew="w108" sw="w102">South Africa</part>
    </parts>
  </ent>
  <ent id="rb2" tref="present" type="date">
    <parts>
      <part ew="w421" sw="w421">now</part>
    </parts>
  </ent>
  <ent id="rb3" type="location" lat="" long="" gazref="">
    <parts>
      <part ew="w458" sw="w458">Paarl</part>
    </parts>
  </ent>
  <ent id="rb4" type="location" lat="" long="" gazref="">
    <parts>
      <part ew="w532" sw="w532">Groenberg</part>
    </parts>
  </ent>
  <ent id="rb5" type="location" lat="" long="" gazref="">
    <parts>
      <part ew="w569" sw="w562">Kromme Rivier</part>
    </parts>
  </ent>
  <ent id="rb7" type="location" lat="" long="" gazref="">
    <parts>
      <part ew="w787" sw="w774">Bain's Kloof Pass</part>
    </parts>
  </ent>
  <ent id="rb8" type="person">
    <parts>
      <part ew="w836" sw="w822">Andrew Geddes Bain</part>
    </parts>
  </ent>
</ents>
<ents source="events">
  <ent id="ev1" subtype="" nominal="true" type="event"><parts><part ew="w77" sw="w77">drive</part></parts></ent>
  <ent tense="pres" voice="pass" asp="simple" modal="no" id="ev2" subtype="center" type="event"><parts><part ew="w182" sw="w182">centered</part></parts></ent>
  <ent tense="pres" voice="pass" asp="simple" modal="no" id="ev3" subtype="locate" type="event"><parts><part ew="w285" sw="w285">located</part></parts></ent>
  <ent tense="nonfin" voice="pass" asp="simple" modal="no" id="ev4" subtype="reach" type="event"><parts><part ew="w324" sw="w324">reached</part></parts></ent>
  <ent tense="pres" voice="act" asp="simple" modal="no" id="ev5" subtype="form" type="event"><parts><part ew="w425" sw="w425">forms</part></parts></ent>
  <ent tense="pres" voice="pass" asp="simple" modal="no" id="ev6" subtype="situate" type="event"><parts><part ew="w504" sw="w504">situated</part></parts></ent>
  <ent tense="pres" voice="act" asp="simple" modal="no" id="ev7" subtype="form" type="event"><parts><part ew="w603" sw="w603">forms</part></parts></ent>
  <ent tense="nonfin" voice="pass" asp="simple" modal="no" id="ev8" subtype="build" type="event"><parts><part ew="w793" sw="w793">built</part></parts></ent>
</ents>
<relations source="temprel">
  <relation id="rbr1" type="simultaneous" text="now forms">
    <argument arg1="true" ref="ev5"/>
    <argument arg2="true" ref="rb2"/>
  </relation>
</relations></standoff></document>
