<placenames>
 <placename id="rb1" name="Butler County"/>
 <placename id="rb2" name="U.S." altname="US" abbrev-for="United States"/>
 <placename id="rb3" name="Ohio"/>
 <placename id="rb5" name="Its county" altname="Its"/>
 <placename id="rb6" name="Hamilton"/>
 <placename id="rb12" name="Cincinnati"/>
 <placename id="rb13" name="OH-KY-IN Metropolitan" altname="OH-KY-IN"/>
 <placename id="rb14" name="the Americas"/>
 <placename id="rb15" name="Miami River"/>
 <placename id="rb19" name="Greenville"/>
 <placename id="rb22" name="Hamilton County"/>
 <placename id="rb30" name="Warren County"/>
</placenames>
