<?xml version="1.0" encoding="UTF-8"?>
<data date-time-format="iso8601">
  <event start="0000-00-00T00:00:00Z" title="established in 1965">
    First established in 1965 as a summer resort town, the community evolved into a retirement community, and continues to change following incorporation in 2006.
  </event>
  <event start="0000-00-00T00:00:00Z" title="summer resort town, the community evolved">
    First established in 1965 as a summer resort town, the community evolved into a retirement community, and continues to change following incorporation in 2006.
  </event>
  <event start="0000-00-00T00:00:00Z" title="began in 1977">
    The city's struggle with incorporation began in 1977 and periodically returned as the community grew rapidly.
  </event>
  <event start="0000-00-00T00:00:00Z" title="a population and building boom in recent years">
    The city has been experiencing a population and building boom in recent years, as indicated by a 60% growth in population between the 2000 and 2010 censuses.
  </event>
  <event start="0000-00-00T00:00:00Z" title="indicated by a 60% growth in population between the 2000">
    The city has been experiencing a population and building boom in recent years, as indicated by a 60% growth in population between the 2000 and 2010 censuses.
  </event>
</data>
